start_case_reporter/__init__.py
start_case_reporter/funcs/auth.py
start_case_reporter/main.py
start_case_reporter-0.1.28.dist-info/entry_points.txt
start_case_reporter-0.1.28.dist-info/METADATA
start_case_reporter-0.1.28.dist-info/WHEEL
start_case_reporter-0.1.28.dist-info/RECORD
